[{"categories":["blog"],"content":"Emily 简介 I’m a girl, a beautiful girl. ","date":"2021-11-27","objectID":"/about/:1:0","tags":["party"],"title":"About","uri":"/about/"},{"categories":["blog"],"content":"这是我的博客，欢迎大家观阅。 ","date":"2021-11-27","objectID":"/second/:0:0","tags":["party"],"title":"Second","uri":"/second/"},{"categories":["blog"],"content":"这是我的标题 这是我的内容 $ pwd /root ","date":"2021-11-27","objectID":"/second/:1:0","tags":["party"],"title":"Second","uri":"/second/"},{"categories":["blog"],"content":"My name my name is emily. ","date":"2021-11-27","objectID":"/first/:1:0","tags":["demo"],"title":"First","uri":"/first/"}]